hyperflask_auth/__init__.py
hyperflask_auth/blueprint.py
hyperflask_auth/captcha.py
hyperflask_auth/emails/auth/forgot_password.mjml
hyperflask_auth/emails/auth/login_link.mjml
hyperflask_auth/flow.py
hyperflask_auth/jinja_ext.py
hyperflask_auth/model.py
hyperflask_auth/pages/__init__.py
hyperflask_auth/pages/connect.py
hyperflask_auth/pages/forgot_password.py
hyperflask_auth/pages/login.py
hyperflask_auth/pages/login_link.py
hyperflask_auth/pages/logout.py
hyperflask_auth/pages/reset_password.py
hyperflask_auth/pages/signup.py
hyperflask_auth/passlib.py
hyperflask_auth/signals.py
hyperflask_auth/templates/auth/connect.html
hyperflask_auth/templates/auth/forgot_password.html
hyperflask_auth/templates/auth/layout.html
hyperflask_auth/templates/auth/login.html
hyperflask_auth/templates/auth/login_link.html
hyperflask_auth/templates/auth/recaptcha.html
hyperflask_auth/templates/auth/reset_password.html
hyperflask_auth/templates/auth/signup.html
hyperflask_auth-0.1.2.dist-info/METADATA
hyperflask_auth-0.1.2.dist-info/WHEEL
hyperflask_auth-0.1.2.dist-info/entry_points.txt
hyperflask_auth-0.1.2.dist-info/RECORD
